{
  "description": "Zone active confirmation — typical .co.uk customer",
  "template": "domain-zone-active",
  "values": {
    "customerName": "Alex",
    "domain": "alexsbakery.co.uk"
  },
  "expected": {
    "subject": "alexsbakery.co.uk is verified — ready for launch ✓",
    "body": "Hi Alex,\n\nYour domain alexsbakery.co.uk is now verified and connected to Cloudflare.\n\nNext up: I'll deploy your site to this domain when you give the\ngreen light on the final review step in your onboarding hub. You'll\nget one more email from me when the site goes live.\n\n— Cowork (your ModuForge ops assistant)"
  }
}
